{
	"data": {
		"state": "success",
		"typeBeanList": [
			{
				"typeId": 1,
				"typeName": "Yuki原创",
				"typePicUrl": "http://yukicomic-pic.oss-cn-hangzhou.aliyuncs.com/yukiicon_20170913175147344903.png",
				"typeTitle": null
			}, {
				"typeId": 6,
				"typeName": "3C数码",
				"typePicUrl": "http://yukicomic-pic.oss-cn-hangzhou.aliyuncs.com/yukiicon_20170612172626803265.png",
				"typeTitle": null
			}, {
				"typeId": 4,
				"typeName": "品质生活",
				"typePicUrl": "http://yukicomic-pic.oss-cn-hangzhou.aliyuncs.com/yukiicon_20170612172611544857.png",
				"typeTitle": null
			}, {
				"typeId": 5,
				"typeName": "文具耗材",
				"typePicUrl": "http://yukicomic-pic.oss-cn-hangzhou.aliyuncs.com/yukiicon_20170612173024022014.png",
				"typeTitle": null
			}, {
				"typeId": 2,
				"typeName": "服鞋箱包",
				"typePicUrl": "http://yukicomic-pic.oss-cn-hangzhou.aliyuncs.com/yukiicon_20170612172554218421.png",
				"typeTitle": null
			}, {
				"typeId": 3,
				"typeName": "家用电器",
				"typePicUrl": "http://yukicomic-pic.oss-cn-hangzhou.aliyuncs.com/yukiicon_20170612172605250450.png",
				"typeTitle": null
			}, {
				"typeId": 7,
				"typeName": "影视动漫周边",
				"typePicUrl": "http://yukicomic-pic.oss-cn-hangzhou.aliyuncs.com/yukiicon_20170612172632149881.png",
				"typeTitle": null
			}
		]
	}
}